rpi_devices/devices.py
rpi_devices/__init__.py
rpi_devices-0.1.0.dist-info/top_level.txt
rpi_devices-0.1.0.dist-info/RECORD
rpi_devices-0.1.0.dist-info/METADATA
rpi_devices-0.1.0.dist-info/WHEEL
rpi_devices-0.1.0.dist-info/DESCRIPTION.rst
rpi_devices-0.1.0.dist-info/metadata.json
