Metadata-Version: 2.0
Name: rpi-devices
Version: 0.1.0
Summary: A library for operating devices connected to a Raspberry Pi
Home-page: https://github.com/munircontractor/raspberry-pi-device-library
Author: Munir Contractor
Author-email: munircontractor@gmail.com
License: LGPLv3
Keywords: raspberrypi,GPIO
Platform: UNKNOWN
Classifier: Development Status :: 3 - Alpha
Classifier: Intended Audience :: Developers
Classifier: Intended Audience :: Information Technology
Classifier: Programming Language :: Python :: 3
Classifier: Programming Language :: Python :: 3.4
Classifier: Programming Language :: Python :: 3.5
Classifier: License :: OSI Approved :: GNU Lesser General Public License v3 or later (LGPLv3+)
Classifier: Topic :: Scientific/Engineering
Classifier: Topic :: Software Development :: Embedded Systems
Requires-Dist: RPi.GPIO
